MANIFEST.in
README.md
setup.py
./src/c/add.c
./src/c/array_add.c
./src/pyc/_add.c
./src/pyc/_array_add.c
./src/pyc/_array_info.c
addc/__init__.py
addc.egg-info/PKG-INFO
addc.egg-info/SOURCES.txt
addc.egg-info/dependency_links.txt
addc.egg-info/requires.txt
addc.egg-info/top_level.txt
addc/c/__init__.py
addc/core/__init__.py
addc/core/add.py
src/c/add.c
src/c/array_add.c
src/include/add.h
src/include/array_add.h
src/pyc/_add.c
src/pyc/_array_add.c
src/pyc/_array_info.c