Metadata-Version: 1.0
Name: addc
Version: 0.0.1a1
Summary: Test C ext
Home-page: https://github.com/jam31118/pycext
Author: sahn
Author-email: jam31118@gmail.com
License: GPLv3
Platform: UNKNOWN
